godocs_jinja/main.py
godocs_jinja/py.typed
godocs_jinja/cli/__init__.py
godocs_jinja/cli/command.py
godocs_jinja/constructor/__init__.py
godocs_jinja/constructor/constructor.py
godocs_jinja/constructor/models/__init__.py
godocs_jinja/constructor/models/rst/__init__.py
godocs_jinja/constructor/models/rst/filters.py
godocs_jinja/constructor/models/rst/templates/class/constant_descriptions.jinja
godocs_jinja/constructor/models/rst/templates/class/description.jinja
godocs_jinja/constructor/models/rst/templates/class/enum_descriptions.jinja
godocs_jinja/constructor/models/rst/templates/class/heading.jinja
godocs_jinja/constructor/models/rst/templates/class/index.jinja
godocs_jinja/constructor/models/rst/templates/class/method_descriptions.jinja
godocs_jinja/constructor/models/rst/templates/class/method_index.jinja
godocs_jinja/constructor/models/rst/templates/class/property_descriptions.jinja
godocs_jinja/constructor/models/rst/templates/class/property_index.jinja
godocs_jinja/constructor/models/rst/templates/class/signal_descriptions.jinja
godocs_jinja/constructor/models/rst/templates/index/index.jinja
godocs_jinja-0.1.2.dist-info/licenses/LICENSE
godocs_jinja-0.1.2.dist-info/METADATA
godocs_jinja-0.1.2.dist-info/WHEEL
godocs_jinja-0.1.2.dist-info/entry_points.txt
godocs_jinja-0.1.2.dist-info/top_level.txt
godocs_jinja-0.1.2.dist-info/RECORD
