Metadata-Version: 2.4
Name: godocs-jinja
Version: 0.1.2
Summary: Jinja implementation of constructor for Godocs CLI
Author-email: "Daniel Sousa (nadjiel)" <oliveira.daaaaniel@gmail.com>
License-Expression: MIT
Project-URL: Homepage, https://github.com/godocs-godot/godocs-jinja
Project-URL: Issues, https://github.com/godocs-godot/godocs-jinja/issues
Keywords: python,godot,documentation,docs,godocs,sphinx,jinja2
Classifier: Programming Language :: Python :: 3
Classifier: Operating System :: OS Independent
Classifier: Development Status :: 4 - Beta
Classifier: Intended Audience :: Developers
Classifier: Natural Language :: English
Requires-Python: >=3.0
License-File: LICENSE
Requires-Dist: jinja2<4.0.0,>=3.1.6
Provides-Extra: dev
Requires-Dist: build; extra == "dev"
Requires-Dist: twine; extra == "dev"
Requires-Dist: pytest<9.0.0,>=8.4.1; extra == "dev"
Provides-Extra: peer
Requires-Dist: godocs<1.0.0,>=0.0.1; extra == "peer"
Dynamic: license-file
